simpleCan/__init__.py
simpleCan/dll_file/vxlapi64.dll
simpleCan/util/__init__.py
simpleCan/util/can_func.py
simpleCan/util/dataStructure.py
simpleCan/util/dbcReader.py
simpleCan/util/messageList.py
simpleCan/util/task.py
simpleCan/util/xldriver.py
simpleCan-2.4.5.dist-info/METADATA
simpleCan-2.4.5.dist-info/WHEEL
simpleCan-2.4.5.dist-info/top_level.txt
simpleCan-2.4.5.dist-info/RECORD
