Metadata-Version: 2.1
Name: simpleCan
Version: 2.4.5
Summary: This package realizes sending and receiving can message functionality. Since 1.9.0 version, DBC file can be chosen to be loaded when initializing simpleCan instance, so that you can send & receive message based on information provided by DBC file2.3.0 Updating channel index issue. Now whenever an instance is created, channel index should be assigned as list2.3.1 check if DBC initial value is greater than maximum value2.3.2 check if DBC signal.raw_initial or scale is none
Author: JIAJIE LIU
Author-email: ljj26god@163.com
Classifier: Programming Language :: Python :: 3
Classifier: License :: OSI Approved :: MIT License
Classifier: Operating System :: OS Independent
Requires-Python: >=3.6
Requires-Dist: cantools
